DisWebhook/Errors.py
DisWebhook/Webhook.py
DisWebhook/__init__.py
DisWebhook/tools.py
DisWebhook-0.1.0.dist-info/LICENCE.txt
DisWebhook-0.1.0.dist-info/METADATA
DisWebhook-0.1.0.dist-info/WHEEL
DisWebhook-0.1.0.dist-info/top_level.txt
DisWebhook-0.1.0.dist-info/RECORD
