Metadata-Version: 2.1
Name: DisWebhook
Version: 0.1.0
Summary: a easy tool for discord webhooks
Home-page: UNKNOWN
Author: Alawi Hussein Adnan Al Sayegh
Author-email: programming.laboratorys@gmail.com
License: MIT
Keywords: DisWebhook,webhooker,diswebhook,webbot,webhook,discord,webdiscord
Platform: UNKNOWN
Classifier: Development Status :: 5 - Production/Stable
Classifier: Intended Audience :: Developers
Classifier: Operating System :: Microsoft :: Windows :: Windows 10
Classifier: Operating System :: POSIX
Classifier: License :: OSI Approved :: MIT License
Classifier: Programming Language :: Python :: 3
Requires-Dist: ColorCraft
